autoviv/__init__.py
python_autoviv-1.0.4.dist-info/METADATA
python_autoviv-1.0.4.dist-info/WHEEL
python_autoviv-1.0.4.dist-info/RECORD
