Metadata-Version: 2.3
Name: python-autoviv
Version: 1.0.4
Summary: 
License: MIT
Author: Tyson Holub
Author-email: tyson@tysonholub.com
Requires-Python: >=3.10,<4.0
Classifier: License :: OSI Approved :: MIT License
Classifier: Programming Language :: Python :: 3
Classifier: Programming Language :: Python :: 3.10
Classifier: Programming Language :: Python :: 3.11
Classifier: Programming Language :: Python :: 3.12
Classifier: Programming Language :: Python :: 3.13
Requires-Dist: typer (>=0.13,<0.14)
Project-URL: homepage, https://gitlab.com/tysonholub/python-autoviv
